{
    "description": "nothing",
    "labels": {
        "0": "background",
        "1": "IA"
    },
    "licence": "see CellPress license",
    "modality": {
        "0": "CT",
        "1": "HU100200",
        "2": "HU200800"
    },
    "name": "CellPress",
    "numTest": 566,
    "numTraining": 0,
    "reference": "see CellPress",
    "release": "0.0",
    "tensorImageSize": "4D",
    "test": [
        "./imagesTs/XJTsN0000.nii.gz",
        "./imagesTs/XJTsN0001.nii.gz",
        "./imagesTs/XJTsN0002.nii.gz",
        "./imagesTs/XJTsN0003.nii.gz",
        "./imagesTs/XJTsN0004.nii.gz",
        "./imagesTs/XJTsN0005.nii.gz",
        "./imagesTs/XJTsN0006.nii.gz",
        "./imagesTs/XJTsN0007.nii.gz",
        "./imagesTs/XJTsN0008.nii.gz",
        "./imagesTs/XJTsN0009.nii.gz",
        "./imagesTs/XJTsN0010.nii.gz",
        "./imagesTs/XJTsN0011.nii.gz",
        "./imagesTs/XJTsN0012.nii.gz",
        "./imagesTs/XJTsN0013.nii.gz",
        "./imagesTs/XJTsN0014.nii.gz",
        "./imagesTs/XJTsN0015.nii.gz",
        "./imagesTs/XJTsN0016.nii.gz",
        "./imagesTs/XJTsN0017.nii.gz",
        "./imagesTs/XJTsN0018.nii.gz",
        "./imagesTs/XJTsN0019.nii.gz",
        "./imagesTs/XJTsN0020.nii.gz",
        "./imagesTs/XJTsN0021.nii.gz",
        "./imagesTs/XJTsN0022.nii.gz",
        "./imagesTs/XJTsN0023.nii.gz",
        "./imagesTs/XJTsN0024.nii.gz",
        "./imagesTs/XJTsN0025.nii.gz",
        "./imagesTs/XJTsN0026.nii.gz",
        "./imagesTs/XJTsN0027.nii.gz",
        "./imagesTs/XJTsN0028.nii.gz",
        "./imagesTs/XJTsN0029.nii.gz",
        "./imagesTs/XJTsN0030.nii.gz",
        "./imagesTs/XJTsN0031.nii.gz",
        "./imagesTs/XJTsN0032.nii.gz",
        "./imagesTs/XJTsN0033.nii.gz",
        "./imagesTs/XJTsN0034.nii.gz",
        "./imagesTs/XJTsN0035.nii.gz",
        "./imagesTs/XJTsN0036.nii.gz",
        "./imagesTs/XJTsN0037.nii.gz",
        "./imagesTs/XJTsN0038.nii.gz",
        "./imagesTs/XJTsN0039.nii.gz",
        "./imagesTs/XJTsN0040.nii.gz",
        "./imagesTs/XJTsN0041.nii.gz",
        "./imagesTs/XJTsN0042.nii.gz",
        "./imagesTs/XJTsN0043.nii.gz",
        "./imagesTs/XJTsN0044.nii.gz",
        "./imagesTs/XJTsN0045.nii.gz",
        "./imagesTs/XJTsN0046.nii.gz",
        "./imagesTs/XJTsN0047.nii.gz",
        "./imagesTs/XJTsN0048.nii.gz",
        "./imagesTs/XJTsN0049.nii.gz",
        "./imagesTs/XJTsN0050.nii.gz",
        "./imagesTs/XJTsN0051.nii.gz",
        "./imagesTs/XJTsN0052.nii.gz",
        "./imagesTs/XJTsN0053.nii.gz",
        "./imagesTs/XJTsN0054.nii.gz",
        "./imagesTs/XJTsN0055.nii.gz",
        "./imagesTs/XJTsN0056.nii.gz",
        "./imagesTs/XJTsN0057.nii.gz",
        "./imagesTs/XJTsN0058.nii.gz",
        "./imagesTs/XJTsN0059.nii.gz",
        "./imagesTs/XJTsN0060.nii.gz",
        "./imagesTs/XJTsN0061.nii.gz",
        "./imagesTs/XJTsN0062.nii.gz",
        "./imagesTs/XJTsN0063.nii.gz",
        "./imagesTs/XJTsN0064.nii.gz",
        "./imagesTs/XJTsN0065.nii.gz",
        "./imagesTs/XJTsN0066.nii.gz",
        "./imagesTs/XJTsN0067.nii.gz",
        "./imagesTs/XJTsN0068.nii.gz",
        "./imagesTs/XJTsN0069.nii.gz",
        "./imagesTs/XJTsN0070.nii.gz",
        "./imagesTs/XJTsN0071.nii.gz",
        "./imagesTs/XJTsN0072.nii.gz",
        "./imagesTs/XJTsN0073.nii.gz",
        "./imagesTs/XJTsN0074.nii.gz",
        "./imagesTs/XJTsN0075.nii.gz",
        "./imagesTs/XJTsN0076.nii.gz",
        "./imagesTs/XJTsN0077.nii.gz",
        "./imagesTs/XJTsN0078.nii.gz",
        "./imagesTs/XJTsN0079.nii.gz",
        "./imagesTs/XJTsN0080.nii.gz",
        "./imagesTs/XJTsN0081.nii.gz",
        "./imagesTs/XJTsN0082.nii.gz",
        "./imagesTs/XJTsN0083.nii.gz",
        "./imagesTs/XJTsN0084.nii.gz",
        "./imagesTs/XJTsN0085.nii.gz",
        "./imagesTs/XJTsN0086.nii.gz",
        "./imagesTs/XJTsN0087.nii.gz",
        "./imagesTs/XJTsN0088.nii.gz",
        "./imagesTs/XJTsN0089.nii.gz",
        "./imagesTs/XJTsN0090.nii.gz",
        "./imagesTs/XJTsN0091.nii.gz",
        "./imagesTs/XJTsN0092.nii.gz",
        "./imagesTs/XJTsN0093.nii.gz",
        "./imagesTs/XJTsN0094.nii.gz",
        "./imagesTs/XJTsN0095.nii.gz",
        "./imagesTs/XJTsN0096.nii.gz",
        "./imagesTs/XJTsN0097.nii.gz",
        "./imagesTs/XJTsN0098.nii.gz",
        "./imagesTs/XJTsN0099.nii.gz",
        "./imagesTs/XJTsN0100.nii.gz",
        "./imagesTs/XJTsN0101.nii.gz",
        "./imagesTs/XJTsN0102.nii.gz",
        "./imagesTs/XJTsN0103.nii.gz",
        "./imagesTs/XJTsN0104.nii.gz",
        "./imagesTs/XJTsN0105.nii.gz",
        "./imagesTs/XJTsN0106.nii.gz",
        "./imagesTs/XJTsN0107.nii.gz",
        "./imagesTs/XJTsN0108.nii.gz",
        "./imagesTs/XJTsN0109.nii.gz",
        "./imagesTs/XJTsN0110.nii.gz",
        "./imagesTs/XJTsN0111.nii.gz",
        "./imagesTs/XJTsN0112.nii.gz",
        "./imagesTs/XJTsN0113.nii.gz",
        "./imagesTs/XJTsN0114.nii.gz",
        "./imagesTs/XJTsN0115.nii.gz",
        "./imagesTs/XJTsN0116.nii.gz",
        "./imagesTs/XJTsN0117.nii.gz",
        "./imagesTs/XJTsN0118.nii.gz",
        "./imagesTs/XJTsN0119.nii.gz",
        "./imagesTs/XJTsN0120.nii.gz",
        "./imagesTs/XJTsN0121.nii.gz",
        "./imagesTs/XJTsN0122.nii.gz",
        "./imagesTs/XJTsN0123.nii.gz",
        "./imagesTs/XJTsN0124.nii.gz",
        "./imagesTs/XJTsN0125.nii.gz",
        "./imagesTs/XJTsN0126.nii.gz",
        "./imagesTs/XJTsN0127.nii.gz",
        "./imagesTs/XJTsN0128.nii.gz",
        "./imagesTs/XJTsN0129.nii.gz",
        "./imagesTs/XJTsN0130.nii.gz",
        "./imagesTs/XJTsN0131.nii.gz",
        "./imagesTs/XJTsN0132.nii.gz",
        "./imagesTs/XJTsN0133.nii.gz",
        "./imagesTs/XJTsN0134.nii.gz",
        "./imagesTs/XJTsN0135.nii.gz",
        "./imagesTs/XJTsN0136.nii.gz",
        "./imagesTs/XJTsN0137.nii.gz",
        "./imagesTs/XJTsN0138.nii.gz",
        "./imagesTs/XJTsN0139.nii.gz",
        "./imagesTs/XJTsN0140.nii.gz",
        "./imagesTs/XJTsN0141.nii.gz",
        "./imagesTs/XJTsN0142.nii.gz",
        "./imagesTs/XJTsN0143.nii.gz",
        "./imagesTs/XJTsN0144.nii.gz",
        "./imagesTs/XJTsN0145.nii.gz",
        "./imagesTs/XJTsN0146.nii.gz",
        "./imagesTs/XJTsN0147.nii.gz",
        "./imagesTs/XJTsN0148.nii.gz",
        "./imagesTs/XJTsN0149.nii.gz",
        "./imagesTs/XJTsN0150.nii.gz",
        "./imagesTs/XJTsN0151.nii.gz",
        "./imagesTs/XJTsN0152.nii.gz",
        "./imagesTs/XJTsN0153.nii.gz",
        "./imagesTs/XJTsN0154.nii.gz",
        "./imagesTs/XJTsN0155.nii.gz",
        "./imagesTs/XJTsN0156.nii.gz",
        "./imagesTs/XJTsN0157.nii.gz",
        "./imagesTs/XJTsN0158.nii.gz",
        "./imagesTs/XJTsN0159.nii.gz",
        "./imagesTs/XJTsN0160.nii.gz",
        "./imagesTs/XJTsN0161.nii.gz",
        "./imagesTs/XJTsN0162.nii.gz",
        "./imagesTs/XJTsN0163.nii.gz",
        "./imagesTs/XJTsN0164.nii.gz",
        "./imagesTs/XJTsN0165.nii.gz",
        "./imagesTs/XJTsN0166.nii.gz",
        "./imagesTs/XJTsN0167.nii.gz",
        "./imagesTs/XJTsN0168.nii.gz",
        "./imagesTs/XJTsN0169.nii.gz",
        "./imagesTs/XJTsN0170.nii.gz",
        "./imagesTs/XJTsN0171.nii.gz",
        "./imagesTs/XJTsN0172.nii.gz",
        "./imagesTs/XJTsN0173.nii.gz",
        "./imagesTs/XJTsN0174.nii.gz",
        "./imagesTs/XJTsN0175.nii.gz",
        "./imagesTs/XJTsN0176.nii.gz",
        "./imagesTs/XJTsN0177.nii.gz",
        "./imagesTs/XJTsN0178.nii.gz",
        "./imagesTs/XJTsN0179.nii.gz",
        "./imagesTs/XJTsN0180.nii.gz",
        "./imagesTs/XJTsN0181.nii.gz",
        "./imagesTs/XJTsN0182.nii.gz",
        "./imagesTs/XJTsN0183.nii.gz",
        "./imagesTs/XJTsN0184.nii.gz",
        "./imagesTs/XJTsN0185.nii.gz",
        "./imagesTs/XJTsN0186.nii.gz",
        "./imagesTs/XJTsN0187.nii.gz",
        "./imagesTs/XJTsN0188.nii.gz",
        "./imagesTs/XJTsN0189.nii.gz",
        "./imagesTs/XJTsN0190.nii.gz",
        "./imagesTs/XJTsN0191.nii.gz",
        "./imagesTs/XJTsN0192.nii.gz",
        "./imagesTs/XJTsN0193.nii.gz",
        "./imagesTs/XJTsN0194.nii.gz",
        "./imagesTs/XJTsN0195.nii.gz",
        "./imagesTs/XJTsN0196.nii.gz",
        "./imagesTs/XJTsN0197.nii.gz",
        "./imagesTs/XJTsN0198.nii.gz",
        "./imagesTs/XJTsN0199.nii.gz",
        "./imagesTs/XJTsN0200.nii.gz",
        "./imagesTs/XJTsN0201.nii.gz",
        "./imagesTs/XJTsN0202.nii.gz",
        "./imagesTs/XJTsN0203.nii.gz",
        "./imagesTs/XJTsN0204.nii.gz",
        "./imagesTs/XJTsN0205.nii.gz",
        "./imagesTs/XJTsN0206.nii.gz",
        "./imagesTs/XJTsN0207.nii.gz",
        "./imagesTs/XJTsN0208.nii.gz",
        "./imagesTs/XJTsN0209.nii.gz",
        "./imagesTs/XJTsN0210.nii.gz",
        "./imagesTs/XJTsN0211.nii.gz",
        "./imagesTs/XJTsN0212.nii.gz",
        "./imagesTs/XJTsN0213.nii.gz",
        "./imagesTs/XJTsN0214.nii.gz",
        "./imagesTs/XJTsN0215.nii.gz",
        "./imagesTs/XJTsN0216.nii.gz",
        "./imagesTs/XJTsN0217.nii.gz",
        "./imagesTs/XJTsN0218.nii.gz",
        "./imagesTs/XJTsN0219.nii.gz",
        "./imagesTs/XJTsN0220.nii.gz",
        "./imagesTs/XJTsN0221.nii.gz",
        "./imagesTs/XJTsN0222.nii.gz",
        "./imagesTs/XJTsN0223.nii.gz",
        "./imagesTs/XJTsN0224.nii.gz",
        "./imagesTs/XJTsN0225.nii.gz",
        "./imagesTs/XJTsN0226.nii.gz",
        "./imagesTs/XJTsN0227.nii.gz",
        "./imagesTs/XJTsN0228.nii.gz",
        "./imagesTs/XJTsN0229.nii.gz",
        "./imagesTs/XJTsN0230.nii.gz",
        "./imagesTs/XJTsN0231.nii.gz",
        "./imagesTs/XJTsN0232.nii.gz",
        "./imagesTs/XJTsN0233.nii.gz",
        "./imagesTs/XJTsN0234.nii.gz",
        "./imagesTs/XJTsN0235.nii.gz",
        "./imagesTs/XJTsN0236.nii.gz",
        "./imagesTs/XJTsN0237.nii.gz",
        "./imagesTs/XJTsN0238.nii.gz",
        "./imagesTs/XJTsN0239.nii.gz",
        "./imagesTs/XJTsN0240.nii.gz",
        "./imagesTs/XJTsN0241.nii.gz",
        "./imagesTs/XJTsN0242.nii.gz",
        "./imagesTs/XJTsN0243.nii.gz",
        "./imagesTs/XJTsN0244.nii.gz",
        "./imagesTs/XJTsN0245.nii.gz",
        "./imagesTs/XJTsN0246.nii.gz",
        "./imagesTs/XJTsN0247.nii.gz",
        "./imagesTs/XJTsN0248.nii.gz",
        "./imagesTs/XJTsN0249.nii.gz",
        "./imagesTs/XJTsN0250.nii.gz",
        "./imagesTs/XJTsN0251.nii.gz",
        "./imagesTs/XJTsN0252.nii.gz",
        "./imagesTs/XJTsN0253.nii.gz",
        "./imagesTs/XJTsN0254.nii.gz",
        "./imagesTs/XJTsN0255.nii.gz",
        "./imagesTs/XJTsN0256.nii.gz",
        "./imagesTs/XJTsN0257.nii.gz",
        "./imagesTs/XJTsN0258.nii.gz",
        "./imagesTs/XJTsN0259.nii.gz",
        "./imagesTs/XJTsN0260.nii.gz",
        "./imagesTs/XJTsN0261.nii.gz",
        "./imagesTs/XJTsN0262.nii.gz",
        "./imagesTs/XJTsN0263.nii.gz",
        "./imagesTs/XJTsN0264.nii.gz",
        "./imagesTs/XJTsN0265.nii.gz",
        "./imagesTs/XJTsN0266.nii.gz",
        "./imagesTs/XJTsN0267.nii.gz",
        "./imagesTs/XJTsN0268.nii.gz",
        "./imagesTs/XJTsN0269.nii.gz",
        "./imagesTs/XJTsN0270.nii.gz",
        "./imagesTs/XJTsN0271.nii.gz",
        "./imagesTs/XJTsN0272.nii.gz",
        "./imagesTs/XJTsN0273.nii.gz",
        "./imagesTs/XJTsN0274.nii.gz",
        "./imagesTs/XJTsN0275.nii.gz",
        "./imagesTs/XJTsN0276.nii.gz",
        "./imagesTs/XJTsN0277.nii.gz",
        "./imagesTs/XJTsN0278.nii.gz",
        "./imagesTs/XJTsN0279.nii.gz",
        "./imagesTs/XJTsN0280.nii.gz",
        "./imagesTs/XJTsN0281.nii.gz",
        "./imagesTs/XJTsN0282.nii.gz",
        "./imagesTs/XJTsN0283.nii.gz",
        "./imagesTs/XJTsN0284.nii.gz",
        "./imagesTs/XJTsN0285.nii.gz",
        "./imagesTs/XJTsN0286.nii.gz",
        "./imagesTs/XJTsN0287.nii.gz",
        "./imagesTs/XJTsN0288.nii.gz",
        "./imagesTs/XJTsN0289.nii.gz",
        "./imagesTs/XJTsN0290.nii.gz",
        "./imagesTs/XJTsN0291.nii.gz",
        "./imagesTs/XJTsN0292.nii.gz",
        "./imagesTs/XJTsN0293.nii.gz",
        "./imagesTs/XJTsN0294.nii.gz",
        "./imagesTs/XJTsN0295.nii.gz",
        "./imagesTs/XJTsN0296.nii.gz",
        "./imagesTs/XJTsN0297.nii.gz",
        "./imagesTs/XJTsN0298.nii.gz",
        "./imagesTs/XJTsN0299.nii.gz",
        "./imagesTs/XJTsN0300.nii.gz",
        "./imagesTs/XJTsN0301.nii.gz",
        "./imagesTs/XJTsN0302.nii.gz",
        "./imagesTs/XJTsN0303.nii.gz",
        "./imagesTs/XJTsN0304.nii.gz",
        "./imagesTs/XJTsN0305.nii.gz",
        "./imagesTs/XJTsN0306.nii.gz",
        "./imagesTs/XJTsN0307.nii.gz",
        "./imagesTs/XJTsN0308.nii.gz",
        "./imagesTs/XJTsN0309.nii.gz",
        "./imagesTs/XJTsN0310.nii.gz",
        "./imagesTs/XJTsN0311.nii.gz",
        "./imagesTs/XJTsN0312.nii.gz",
        "./imagesTs/XJTsN0313.nii.gz",
        "./imagesTs/XJTsN0314.nii.gz",
        "./imagesTs/XJTsN0315.nii.gz",
        "./imagesTs/XJTsN0316.nii.gz",
        "./imagesTs/XJTsN0317.nii.gz",
        "./imagesTs/XJTsN0318.nii.gz",
        "./imagesTs/XJTsN0319.nii.gz",
        "./imagesTs/XJTsN0320.nii.gz",
        "./imagesTs/XJTsN0321.nii.gz",
        "./imagesTs/XJTsN0322.nii.gz",
        "./imagesTs/XJTsN0323.nii.gz",
        "./imagesTs/XJTsN0324.nii.gz",
        "./imagesTs/XJTsN0325.nii.gz",
        "./imagesTs/XJTsN0326.nii.gz",
        "./imagesTs/XJTsN0327.nii.gz",
        "./imagesTs/XJTsN0328.nii.gz",
        "./imagesTs/XJTsN0329.nii.gz",
        "./imagesTs/XJTsN0330.nii.gz",
        "./imagesTs/XJTsN0331.nii.gz",
        "./imagesTs/XJTsN0332.nii.gz",
        "./imagesTs/XJTsN0333.nii.gz",
        "./imagesTs/XJTsN0334.nii.gz",
        "./imagesTs/XJTsN0335.nii.gz",
        "./imagesTs/XJTsN0336.nii.gz",
        "./imagesTs/XJTsN0337.nii.gz",
        "./imagesTs/XJTsN0338.nii.gz",
        "./imagesTs/XJTsN0339.nii.gz",
        "./imagesTs/XJTsN0340.nii.gz",
        "./imagesTs/XJTsN0341.nii.gz",
        "./imagesTs/XJTsN0342.nii.gz",
        "./imagesTs/XJTsN0343.nii.gz",
        "./imagesTs/XJTsN0344.nii.gz",
        "./imagesTs/XJTsN0345.nii.gz",
        "./imagesTs/XJTsN0346.nii.gz",
        "./imagesTs/XJTsN0347.nii.gz",
        "./imagesTs/XJTsN0348.nii.gz",
        "./imagesTs/XJTsN0349.nii.gz",
        "./imagesTs/XJTsN0350.nii.gz",
        "./imagesTs/XJTsN0351.nii.gz",
        "./imagesTs/XJTsN0352.nii.gz",
        "./imagesTs/XJTsN0353.nii.gz",
        "./imagesTs/XJTsN0354.nii.gz",
        "./imagesTs/XJTsN0355.nii.gz",
        "./imagesTs/XJTsN0356.nii.gz",
        "./imagesTs/XJTsN0357.nii.gz",
        "./imagesTs/XJTsN0358.nii.gz",
        "./imagesTs/XJTsN0359.nii.gz",
        "./imagesTs/XJTsN0360.nii.gz",
        "./imagesTs/XJTsN0361.nii.gz",
        "./imagesTs/XJTsN0362.nii.gz",
        "./imagesTs/XJTsN0363.nii.gz",
        "./imagesTs/XJTsN0364.nii.gz",
        "./imagesTs/XJTsN0365.nii.gz",
        "./imagesTs/XJTsN0366.nii.gz",
        "./imagesTs/XJTsN0367.nii.gz",
        "./imagesTs/XJTsN0368.nii.gz",
        "./imagesTs/XJTsN0369.nii.gz",
        "./imagesTs/XJTsN0370.nii.gz",
        "./imagesTs/XJTsN0371.nii.gz",
        "./imagesTs/XJTsN0372.nii.gz",
        "./imagesTs/XJTsN0373.nii.gz",
        "./imagesTs/XJTsN0374.nii.gz",
        "./imagesTs/XJTsN0375.nii.gz",
        "./imagesTs/XJTsN0376.nii.gz",
        "./imagesTs/XJTsN0377.nii.gz",
        "./imagesTs/XJTsN0378.nii.gz",
        "./imagesTs/XJTsN0379.nii.gz",
        "./imagesTs/XJTsN0380.nii.gz",
        "./imagesTs/XJTsN0381.nii.gz",
        "./imagesTs/XJTsN0382.nii.gz",
        "./imagesTs/XJTsN0383.nii.gz",
        "./imagesTs/XJTsN0384.nii.gz",
        "./imagesTs/XJTsN0385.nii.gz",
        "./imagesTs/XJTsN0386.nii.gz",
        "./imagesTs/XJTsN0387.nii.gz",
        "./imagesTs/XJTsN0388.nii.gz",
        "./imagesTs/XJTsN0389.nii.gz",
        "./imagesTs/XJTsN0390.nii.gz",
        "./imagesTs/XJTsN0391.nii.gz",
        "./imagesTs/XJTsN0392.nii.gz",
        "./imagesTs/XJTsN0393.nii.gz",
        "./imagesTs/XJTsN0394.nii.gz",
        "./imagesTs/XJTsN0395.nii.gz",
        "./imagesTs/XJTsN0396.nii.gz",
        "./imagesTs/XJTsN0397.nii.gz",
        "./imagesTs/XJTsN0398.nii.gz",
        "./imagesTs/XJTsN0399.nii.gz",
        "./imagesTs/XJTsN0400.nii.gz",
        "./imagesTs/XJTsN0401.nii.gz",
        "./imagesTs/XJTsN0402.nii.gz",
        "./imagesTs/XJTsN0403.nii.gz",
        "./imagesTs/XJTsN0404.nii.gz",
        "./imagesTs/XJTsN0405.nii.gz",
        "./imagesTs/XJTsN0406.nii.gz",
        "./imagesTs/XJTsN0407.nii.gz",
        "./imagesTs/XJTsN0408.nii.gz",
        "./imagesTs/XJTsN0409.nii.gz",
        "./imagesTs/XJTsN0410.nii.gz",
        "./imagesTs/XJTsN0411.nii.gz",
        "./imagesTs/XJTsN0412.nii.gz",
        "./imagesTs/XJTsN0413.nii.gz",
        "./imagesTs/XJTsN0414.nii.gz",
        "./imagesTs/XJTsN0415.nii.gz",
        "./imagesTs/XJTsN0416.nii.gz",
        "./imagesTs/XJTsN0417.nii.gz",
        "./imagesTs/XJTsN0418.nii.gz",
        "./imagesTs/XJTsN0419.nii.gz",
        "./imagesTs/XJTsN0420.nii.gz",
        "./imagesTs/XJTsN0421.nii.gz",
        "./imagesTs/XJTsN0422.nii.gz",
        "./imagesTs/XJTsN0423.nii.gz",
        "./imagesTs/XJTsN0424.nii.gz",
        "./imagesTs/XJTsN0425.nii.gz",
        "./imagesTs/XJTsN0426.nii.gz",
        "./imagesTs/XJTsN0427.nii.gz",
        "./imagesTs/XJTsN0428.nii.gz",
        "./imagesTs/XJTsN0429.nii.gz",
        "./imagesTs/XJTsN0430.nii.gz",
        "./imagesTs/XJTsN0431.nii.gz",
        "./imagesTs/XJTsN0432.nii.gz",
        "./imagesTs/XJTsN0433.nii.gz",
        "./imagesTs/XJTsN0434.nii.gz",
        "./imagesTs/XJTsN0435.nii.gz",
        "./imagesTs/XJTsN0436.nii.gz",
        "./imagesTs/XJTsN0437.nii.gz",
        "./imagesTs/XJTsN0438.nii.gz",
        "./imagesTs/XJTsN0439.nii.gz",
        "./imagesTs/XJTsN0440.nii.gz",
        "./imagesTs/XJTsN0441.nii.gz",
        "./imagesTs/XJTsN0442.nii.gz",
        "./imagesTs/XJTsN0443.nii.gz",
        "./imagesTs/XJTsN0444.nii.gz",
        "./imagesTs/XJTsN0445.nii.gz",
        "./imagesTs/XJTsN0446.nii.gz",
        "./imagesTs/XJTsN0447.nii.gz",
        "./imagesTs/XJTsN0448.nii.gz",
        "./imagesTs/XJTsN0449.nii.gz",
        "./imagesTs/XJTsN0450.nii.gz",
        "./imagesTs/XJTsN0451.nii.gz",
        "./imagesTs/XJTsN0452.nii.gz",
        "./imagesTs/XJTsN0453.nii.gz",
        "./imagesTs/XJTsN0454.nii.gz",
        "./imagesTs/XJTsN0455.nii.gz",
        "./imagesTs/XJTsN0456.nii.gz",
        "./imagesTs/XJTsN0457.nii.gz",
        "./imagesTs/XJTsN0458.nii.gz",
        "./imagesTs/XJTsN0459.nii.gz",
        "./imagesTs/XJTsN0460.nii.gz",
        "./imagesTs/XJTsN0461.nii.gz",
        "./imagesTs/XJTsN0462.nii.gz",
        "./imagesTs/XJTsN0463.nii.gz",
        "./imagesTs/XJTsN0464.nii.gz",
        "./imagesTs/XJTsN0465.nii.gz",
        "./imagesTs/XJTsN0466.nii.gz",
        "./imagesTs/XJTsN0467.nii.gz",
        "./imagesTs/XJTsN0468.nii.gz",
        "./imagesTs/XJTsN0469.nii.gz",
        "./imagesTs/XJTsN0470.nii.gz",
        "./imagesTs/XJTsN0471.nii.gz",
        "./imagesTs/XJTsN0472.nii.gz",
        "./imagesTs/XJTsN0473.nii.gz",
        "./imagesTs/XJTsN0474.nii.gz",
        "./imagesTs/XJTsN0475.nii.gz",
        "./imagesTs/XJTsN0476.nii.gz",
        "./imagesTs/XJTsN0477.nii.gz",
        "./imagesTs/XJTsN0478.nii.gz",
        "./imagesTs/XJTsN0479.nii.gz",
        "./imagesTs/XJTsN0480.nii.gz",
        "./imagesTs/XJTsN0481.nii.gz",
        "./imagesTs/XJTsN0482.nii.gz",
        "./imagesTs/XJTsN0483.nii.gz",
        "./imagesTs/XJTsN0484.nii.gz",
        "./imagesTs/XJTsN0485.nii.gz",
        "./imagesTs/XJTsN0486.nii.gz",
        "./imagesTs/XJTsN0487.nii.gz",
        "./imagesTs/XJTsN0488.nii.gz",
        "./imagesTs/XJTsN0489.nii.gz",
        "./imagesTs/XJTsN0490.nii.gz",
        "./imagesTs/XJTsN0491.nii.gz",
        "./imagesTs/XJTsN0492.nii.gz",
        "./imagesTs/XJTsN0493.nii.gz",
        "./imagesTs/XJTsN0494.nii.gz",
        "./imagesTs/XJTsN0495.nii.gz",
        "./imagesTs/XJTsN0496.nii.gz",
        "./imagesTs/XJTsN0497.nii.gz",
        "./imagesTs/XJTsN0498.nii.gz",
        "./imagesTs/XJTsN0499.nii.gz",
        "./imagesTs/XJTsN0500.nii.gz",
        "./imagesTs/XJTsN0501.nii.gz",
        "./imagesTs/XJTsN0502.nii.gz",
        "./imagesTs/XJTsN0503.nii.gz",
        "./imagesTs/XJTsN0504.nii.gz",
        "./imagesTs/XJTsN0505.nii.gz",
        "./imagesTs/XJTsN0506.nii.gz",
        "./imagesTs/XJTsN0507.nii.gz",
        "./imagesTs/XJTsN0508.nii.gz",
        "./imagesTs/XJTsN0509.nii.gz",
        "./imagesTs/XJTsN0510.nii.gz",
        "./imagesTs/XJTsN0511.nii.gz",
        "./imagesTs/XJTsN0512.nii.gz",
        "./imagesTs/XJTsN0513.nii.gz",
        "./imagesTs/XJTsN0514.nii.gz",
        "./imagesTs/XJTsN0515.nii.gz",
        "./imagesTs/XJTsN0516.nii.gz",
        "./imagesTs/XJTsN0517.nii.gz",
        "./imagesTs/XJTsN0518.nii.gz",
        "./imagesTs/XJTsN0519.nii.gz",
        "./imagesTs/XJTsN0520.nii.gz",
        "./imagesTs/XJTsN0521.nii.gz",
        "./imagesTs/XJTsN0522.nii.gz",
        "./imagesTs/XJTsN0523.nii.gz",
        "./imagesTs/XJTsN0524.nii.gz",
        "./imagesTs/XJTsN0525.nii.gz",
        "./imagesTs/XJTsN0526.nii.gz",
        "./imagesTs/XJTsN0527.nii.gz",
        "./imagesTs/XJTsN0528.nii.gz",
        "./imagesTs/XJTsN0529.nii.gz",
        "./imagesTs/XJTsN0530.nii.gz",
        "./imagesTs/XJTsN0531.nii.gz",
        "./imagesTs/XJTsN0532.nii.gz",
        "./imagesTs/XJTsN0533.nii.gz",
        "./imagesTs/XJTsN0534.nii.gz",
        "./imagesTs/XJTsN0535.nii.gz",
        "./imagesTs/XJTsN0536.nii.gz",
        "./imagesTs/XJTsN0537.nii.gz",
        "./imagesTs/XJTsN0538.nii.gz",
        "./imagesTs/XJTsN0539.nii.gz",
        "./imagesTs/XJTsN0540.nii.gz",
        "./imagesTs/XJTsN0541.nii.gz",
        "./imagesTs/XJTsN0542.nii.gz",
        "./imagesTs/XJTsN0543.nii.gz",
        "./imagesTs/XJTsN0544.nii.gz",
        "./imagesTs/XJTsN0545.nii.gz",
        "./imagesTs/XJTsN0546.nii.gz",
        "./imagesTs/XJTsN0547.nii.gz",
        "./imagesTs/XJTsN0548.nii.gz",
        "./imagesTs/XJTsN0549.nii.gz",
        "./imagesTs/XJTsN0550.nii.gz",
        "./imagesTs/XJTsN0551.nii.gz",
        "./imagesTs/XJTsN0552.nii.gz",
        "./imagesTs/XJTsN0553.nii.gz",
        "./imagesTs/XJTsN0554.nii.gz",
        "./imagesTs/XJTsN0555.nii.gz",
        "./imagesTs/XJTsN0556.nii.gz",
        "./imagesTs/XJTsN0557.nii.gz",
        "./imagesTs/XJTsN0558.nii.gz",
        "./imagesTs/XJTsN0559.nii.gz",
        "./imagesTs/XJTsN0560.nii.gz",
        "./imagesTs/XJTsN0561.nii.gz",
        "./imagesTs/XJTsN0562.nii.gz",
        "./imagesTs/XJTsN0563.nii.gz",
        "./imagesTs/XJTsN0564.nii.gz",
        "./imagesTs/XJTsN0565.nii.gz"
    ],
    "training": []
}